synthetic_data_mcp/__init__.py
synthetic_data_mcp/cli.py
synthetic_data_mcp/run_clean.py
synthetic_data_mcp/server.py
synthetic_data_mcp/compliance/consent_management.py
synthetic_data_mcp/compliance/data_residency.py
synthetic_data_mcp/compliance/regulatory_reporting.py
synthetic_data_mcp/compliance/soc2.py
synthetic_data_mcp/compliance/validator.py
synthetic_data_mcp/config/ollama.py
synthetic_data_mcp/core/generator.py
synthetic_data_mcp/database/__init__.py
synthetic_data_mcp/database/base.py
synthetic_data_mcp/database/manager.py
synthetic_data_mcp/database/migrations.py
synthetic_data_mcp/database/schema_inspector.py
synthetic_data_mcp/database/connectors/__init__.py
synthetic_data_mcp/database/connectors/bigquery.py
synthetic_data_mcp/database/connectors/db2_connector.py
synthetic_data_mcp/database/connectors/dynamodb_connector.py
synthetic_data_mcp/database/connectors/mongodb.py
synthetic_data_mcp/database/connectors/mysql.py
synthetic_data_mcp/database/connectors/postgresql.py
synthetic_data_mcp/database/connectors/redis.py
synthetic_data_mcp/database/connectors/redshift.py
synthetic_data_mcp/database/connectors/snowflake.py
synthetic_data_mcp/database/connectors/vector_connector.py
synthetic_data_mcp/infrastructure/caching.py
synthetic_data_mcp/infrastructure/scaling.py
synthetic_data_mcp/ingestion/__init__.py
synthetic_data_mcp/ingestion/data_ingestion.py
synthetic_data_mcp/ingestion/knowledge_loader.py
synthetic_data_mcp/ingestion/pattern_analyzer.py
synthetic_data_mcp/monitoring/metrics.py
synthetic_data_mcp/privacy/engine.py
synthetic_data_mcp/providers/__init__.py
synthetic_data_mcp/providers/base.py
synthetic_data_mcp/providers/ollama_provider.py
synthetic_data_mcp/providers/openai_provider.py
synthetic_data_mcp/schemas/base.py
synthetic_data_mcp/schemas/finance.py
synthetic_data_mcp/schemas/healthcare.py
synthetic_data_mcp/security/auth.py
synthetic_data_mcp/security/encryption.py
synthetic_data_mcp/utils/audit.py
synthetic_data_mcp-0.1.2.dist-info/licenses/LICENSE
synthetic_data_mcp-0.1.2.dist-info/METADATA
synthetic_data_mcp-0.1.2.dist-info/WHEEL
synthetic_data_mcp-0.1.2.dist-info/entry_points.txt
synthetic_data_mcp-0.1.2.dist-info/top_level.txt
synthetic_data_mcp-0.1.2.dist-info/RECORD
