Metadata-Version: 2.4
Name: synthetic-data-mcp
Version: 0.1.2
Summary: Domain-specific synthetic data generation MCP server for healthcare and finance compliance
Author-email: Marc Shade <marc@2acrestudios.com>
License: MIT
Project-URL: Homepage, https://github.com/marc-shade/synthetic-data-mcp
Project-URL: Documentation, https://synthetic-data-mcp.readthedocs.io
Project-URL: Repository, https://github.com/marc-shade/synthetic-data-mcp
Project-URL: Issues, https://github.com/marc-shade/synthetic-data-mcp/issues
Keywords: synthetic-data,mcp,healthcare,finance,compliance,privacy
Classifier: Development Status :: 3 - Alpha
Classifier: Intended Audience :: Healthcare Industry
Classifier: Intended Audience :: Financial and Insurance Industry
Classifier: Topic :: Scientific/Engineering :: Artificial Intelligence
Classifier: Topic :: Security :: Cryptography
Classifier: License :: OSI Approved :: MIT License
Classifier: Programming Language :: Python :: 3
Classifier: Programming Language :: Python :: 3.10
Classifier: Programming Language :: Python :: 3.11
Classifier: Programming Language :: Python :: 3.12
Classifier: Programming Language :: Python :: 3.13
Requires-Python: >=3.10
License-File: LICENSE
Requires-Dist: fastmcp>=0.1.0
Requires-Dist: fastapi>=0.104.0
Requires-Dist: dspy-ai>=2.4.0
Requires-Dist: pydantic>=2.5.0
Requires-Dist: numpy>=1.24.0
Requires-Dist: pandas>=2.0.0
Requires-Dist: scipy>=1.10.0
Requires-Dist: scikit-learn>=1.3.0
Requires-Dist: cryptography>=41.0.0
Requires-Dist: python-dateutil>=2.8.0
Requires-Dist: faker>=19.0.0
Requires-Dist: sqlalchemy>=2.0.0
Requires-Dist: alembic>=1.12.0
Requires-Dist: pyjwt>=2.8.0
Requires-Dist: httpx>=0.25.0
Requires-Dist: requests>=2.31.0
Requires-Dist: loguru>=0.7.0
Requires-Dist: typer>=0.9.0
Requires-Dist: rich>=13.0.0
Requires-Dist: pytest>=7.4.0
Requires-Dist: pytest-asyncio>=0.21.0
Requires-Dist: aiofiles>=23.2.0
Provides-Extra: dev
Requires-Dist: pytest>=8.4.1; extra == "dev"
Requires-Dist: pytest-asyncio>=0.24.0; extra == "dev"
Requires-Dist: pytest-cov>=5.0.0; extra == "dev"
Requires-Dist: black>=24.8.0; extra == "dev"
Requires-Dist: isort>=5.13.0; extra == "dev"
Requires-Dist: flake8>=7.1.0; extra == "dev"
Requires-Dist: mypy>=1.13.0; extra == "dev"
Requires-Dist: pre-commit>=4.0.0; extra == "dev"
Requires-Dist: ruff>=0.7.0; extra == "dev"
Provides-Extra: healthcare
Requires-Dist: python-hl7>=0.4.0; extra == "healthcare"
Requires-Dist: fhir-py>=0.2.0; extra == "healthcare"
Requires-Dist: pydicom>=2.4.0; extra == "healthcare"
Provides-Extra: finance
Requires-Dist: yfinance>=0.2.0; extra == "finance"
Requires-Dist: fredapi>=0.5.0; extra == "finance"
Requires-Dist: quantlib>=1.31.0; extra == "finance"
Provides-Extra: performance
Requires-Dist: numba>=0.58.0; extra == "performance"
Requires-Dist: dask>=2023.9.0; extra == "performance"
Requires-Dist: ray>=2.7.0; extra == "performance"
Dynamic: license-file
